opensdg/__init__.py
opensdg-1.0.3.dist-info/METADATA
opensdg-1.0.3.dist-info/WHEEL
opensdg-1.0.3.dist-info/top_level.txt
opensdg-1.0.3.dist-info/RECORD
